Metadata-Version: 2.1
Name: odML-UI
Version: 1.4.3
Summary: odML Editor
Home-page: https://github.com/G-Node/odml-ui
Author: Shubham Dighe, Hagen Fritsch, Christian Kellner, Jan Grewe, Achilleas Koutsou, Michael Sonntag
Author-email: dev@g-node.org
License: BSD
Platform: UNKNOWN
Classifier: Development Status :: 4 - Beta
Classifier: Programming Language :: Python
Classifier: Programming Language :: Python :: 3.5
Classifier: Programming Language :: Python :: 3.6
Classifier: Programming Language :: Python :: 3.7
Classifier: Programming Language :: Python :: 3.8
Classifier: Topic :: Scientific/Engineering
Classifier: Intended Audience :: Science/Research
Classifier: Intended Audience :: End Users/Desktop
Classifier: License :: OSI Approved :: BSD License
